nwae/lang/LangFeatures.py
nwae/lang/LangHelper.py
nwae/lang/NwaeLangUnitTest.py
nwae/lang/TextProcessor.py
nwae/lang/characters/LangCharacters.py
nwae/lang/classification/TextClusterBasic.py
nwae/lang/classification/TxtCluster.py
nwae/lang/classification/TxtClusterUnitTest.py
nwae/lang/config/Config.py
nwae/lang/corpora/Scrape.py
nwae/lang/corpora/ScrapeUrl.py
nwae/lang/corpora/TestCorpora.py
nwae/lang/detect/CommonWords.py
nwae/lang/detect/LangDetect.py
nwae/lang/detect/LangDetectUnitTest.py
nwae/lang/detect/comwords/English.py
nwae/lang/detect/comwords/French.py
nwae/lang/detect/comwords/Indonesian.py
nwae/lang/detect/comwords/Spanish.py
nwae/lang/detect/comwords/Vietnamese.py
nwae/lang/model/FeatureVect.py
nwae/lang/model/FeatureVector.py
nwae/lang/model/WordEmbedding.py
nwae/lang/model/WordFreqDocMatrix.py
nwae/lang/nlp/Corpora.py
nwae/lang/nlp/LatinEquivalentForm.py
nwae/lang/nlp/PosTagging.py
nwae/lang/nlp/SynonymList.py
nwae/lang/nlp/WordList.py
nwae/lang/nlp/WordSegmentation.py
nwae/lang/nlp/WordSegmentationModel.py
nwae/lang/nlp/daehua/DaehuaModel.py
nwae/lang/nlp/daehua/DaehuaTrainDataModel.py
nwae/lang/nlp/daehua/forms/DaehuaModelForms.py
nwae/lang/nlp/daehua/forms/Form.py
nwae/lang/nlp/daehua/forms/FormField.py
nwae/lang/nlp/lemma/Lemmatizer.py
nwae/lang/nlp/lemma/LemmatizerBase.py
nwae/lang/nlp/lemma/LemmatizerKorean.py
nwae/lang/nlp/sajun/EditDistance.py
nwae/lang/nlp/sajun/SpellCheckSentence.py
nwae/lang/nlp/sajun/SpellCheckWord.py
nwae/lang/nlp/sajun/TrieNode.py
nwae/lang/nlp/translation/Translator.py
nwae/lang/nlp/ut/UtWordSegmentation.py
nwae/lang/preprocessing/BasicPreprocessor.py
nwae/lang/preprocessing/Stopwordtags.py
nwae/lang/preprocessing/TxtPreprcsrAllLang.py
nwae/lang/preprocessing/TxtPreprocessor.py
nwae/lang/preprocessing/ut/SampleTextClassificationData.py
nwae/lang/preprocessing/ut/UtTxtPreprocessor.py
nwae/lang/speech/recognition/SpeechRecognition.py
nwae/lang/stats/LangStats.py
nwae/lang/stats/WordStats.py
nwae.lang-0.2.9.dist-info/METADATA
nwae.lang-0.2.9.dist-info/WHEEL
nwae.lang-0.2.9.dist-info/top_level.txt
nwae.lang-0.2.9.dist-info/RECORD
