Metadata-Version: 2.1
Name: nwae.lang
Version: 0.2.9
Summary: ML
Home-page: UNKNOWN
Author: nwae
Author-email: mapktah@ya.ru
License: UNKNOWN
Platform: UNKNOWN
Requires-Dist: nwae.utils
Requires-Dist: mex
Requires-Dist: nltk
Requires-Dist: googletrans
